picky/__init__.py
picky/handlers.py
picky/main.py
picky/requirements.py
picky-0.9.2.dist-info/DESCRIPTION.rst
picky-0.9.2.dist-info/entry_points.txt
picky-0.9.2.dist-info/METADATA
picky-0.9.2.dist-info/metadata.json
picky-0.9.2.dist-info/RECORD
picky-0.9.2.dist-info/top_level.txt
picky-0.9.2.dist-info/WHEEL
tests/__init__.py
tests/test_functional.py
tests/test_handlers.py
tests/test_requirements.py
tests/sample_output/conda_list_for_update.py
tests/sample_output/conda_list_simple.py
tests/sample_output/conda_versions.txt
tests/sample_output/pip_freeze_for_combine.py
tests/sample_output/pip_freeze_for_update.py
tests/sample_output/pip_freeze_git.py
tests/sample_output/pip_freeze_no_git.py
tests/sample_output/pip_freeze_no_vcs_remote.py
tests/sample_output/pip_freeze_old.py
tests/sample_output/pip_freeze_simple.py
tests/sample_output/requirements.txt
